ddq_config_manager/__init__.py
ddq_config_manager/config_manager.py
ddq_config_manager/config_panel.py
ddq_config_manager/configurable_tool.py
ddq_widgets/__init__.py
ddq_widgets/ddq_button.py
ddq_widgets/ddq_button_group.py
ddq_widgets/ddq_card.py
ddq_widgets/ddq_checkbox.py
ddq_widgets/ddq_file_picker.py
ddq_widgets/ddq_form.py
ddq_widgets/ddq_form_item.py
ddq_widgets/ddq_input.py
ddq_widgets/ddq_listbox.py
ddq_widgets/ddq_password_input.py
ddq_widgets/ddq_radio.py
ddq_widgets/ddq_scrollable.py
ddq_widgets/ddq_space.py
ddq_widgets/ddq_split_layout.py
ddq_widgets/ddq_table.py
ddq_widgets/ddq_text.py
ddq_widgets/ddq_textarea.py
ddq_widgets/ddq_toast.py
examples/__init__.py
examples/demo.py
examples/demo_button.py
examples/demo_button_group.py
examples/demo_card.py
examples/demo_checkbox.py
examples/demo_file_picker.py
examples/demo_form.py
examples/demo_form_item.py
examples/demo_listbox.py
examples/demo_scrollable_text.py
examples/demo_split_layout.py
examples/demo_table.py
examples/demo_text.py
tests/__init__.py
tests/conftest.py
tests/test_config_manager/__init__.py
tests/test_config_manager/test_config_manager.py
tests/test_config_manager/test_config_panel.py
tests/test_config_manager/test_configurable_tool.py
tests/test_integration/__init__.py
tests/test_widgets/__init__.py
tests/test_widgets/test_button.py
tests/test_widgets/test_button_group.py
tests/test_widgets/test_card.py
tests/test_widgets/test_checkbox.py
tests/test_widgets/test_file_picker.py
tests/test_widgets/test_form.py
tests/test_widgets/test_form_item.py
tests/test_widgets/test_input.py
tests/test_widgets/test_listbox.py
tests/test_widgets/test_password_input.py
tests/test_widgets/test_radio.py
tests/test_widgets/test_split_layout.py
tests/test_widgets/test_table.py
ddq_tkinter-0.3.0.dist-info/METADATA
ddq_tkinter-0.3.0.dist-info/WHEEL
ddq_tkinter-0.3.0.dist-info/top_level.txt
ddq_tkinter-0.3.0.dist-info/RECORD
