Metadata-Version: 2.1
Name: ddq-tkinter
Version: 0.3.0
Requires-Python: >=3.6
Requires-Dist: tkinter
